{"cameraMode":{"drawMode":0,"name":"Shaded","section":"Shading Mode"},"sceneLighting":true,"audioPlay":false,"sceneViewState":{"m_AlwaysRefresh":false,"showFog":true,"showSkybox":true,"showFlares":true,"showImageEffects":true,"showParticleSystems":true,"showVisualEffectGraphs":true,"m_FxEnabled":true},"in2DMode":false,"pivot":{"x":7.982357501983643,"y":-3.923924446105957,"z":-6.757283687591553},"rotation":{"x":0.0854877233505249,"y":0.9043543338775635,"z":-0.21586373448371888,"w":0.3581491708755493},"size":16.457780838012697,"orthographic":false}